{
    "id": "beginner dungeon 2",
    "title": "Beginner Dungeon - Floor #2",
    "level": {
        "width": 20,
        "height": 20,
        "tile_width": 15,
        "tile_height": 15,
        "camera_zoom": 2,
        "tileset": "cave",
        "tiles": [
            "wall", "wall", "wall", "wall", "wall", "wall", "wall", "wall", "wall", "wall", "wall", "wall", "wall", "wall", "wall", "empty", "empty", "empty", "empty", "empty",
            "wall", "stairs down", "ground", "ground", "ground", "ground", "ground", "ground", "ground", "ground", "ground", "ground", "ground", "ground", "wall", "empty", "empty", "empty", "empty", "empty",
            "wall", "wall", "wall", "wall", "wall", "wall", "ground", "ground", "ground", "ground", "ground", "ground", "ground", "ground", "wall", "empty", "empty", "empty", "empty", "empty",
            "empty", "empty", "empty", "empty", "empty", "wall", "ground", "ground", "ground", "ground", "ground", "ground", "ground", "ground", "wall", "empty", "empty", "empty", "empty", "empty",
            "empty", "empty", "empty", "empty", "empty", "wall", "ground", "ground", "ground", "ground", "ground", "ground", "ground", "ground", "wall", "empty", "empty", "empty", "empty", "empty",
            "empty", "empty", "empty", "empty", "empty", "wall", "ground", "ground", "ground", "ground", "ground", "ground", "ground", "ground", "wall", "empty", "empty", "empty", "empty", "empty",
            "empty", "empty", "empty", "empty", "empty", "wall", "ground", "ground", "ground", "ground", "ground", "ground", "ground", "ground", "wall", "empty", "empty", "empty", "empty", "empty",
            "empty", "empty", "empty", "empty", "empty", "wall", "ground", "ground", "ground", "ground", "ground", "ground", "ground", "ground", "wall", "empty", "empty", "empty", "empty", "empty",
            "empty", "empty", "empty", "empty", "empty", "wall", "ground", "ground", "ground", "ground", "ground", "ground", "ground", "ground", "wall", "empty", "empty", "empty", "empty", "empty",
            "empty", "empty", "empty", "empty", "empty", "wall", "ground", "ground", "ground", "ground", "ground", "ground", "ground", "ground", "wall", "empty", "empty", "empty", "empty", "empty",
            "empty", "empty", "empty", "empty", "empty", "wall", "ground", "ground", "ground", "ground", "ground", "ground", "ground", "ground", "wall", "empty", "empty", "empty", "empty", "empty",
            "empty", "empty", "empty", "empty", "empty", "wall", "ground", "ground", "ground", "ground", "ground", "ground", "ground", "ground", "wall", "empty", "empty", "empty", "empty", "empty",
            "empty", "empty", "empty", "empty", "empty", "wall", "ground", "ground", "ground", "ground", "ground", "ground", "ground", "ground", "wall", "empty", "empty", "empty", "empty", "empty",
            "empty", "empty", "empty", "empty", "empty", "wall", "ground", "ground", "ground", "ground", "ground", "ground", "ground", "ground", "wall", "empty", "empty", "empty", "empty", "empty",
            "empty", "empty", "empty", "empty", "empty", "wall", "ground", "ground", "ground", "ground", "ground", "ground", "ground", "ground", "wall", "empty", "empty", "empty", "empty", "empty",
            "empty", "empty", "empty", "empty", "empty", "wall", "ground", "ground", "ground", "ground", "ground", "ground", "ground", "ground", "wall", "empty", "empty", "empty", "empty", "empty",
            "empty", "empty", "empty", "empty", "empty", "wall", "ground", "ground", "ground", "ground", "ground", "ground", "ground", "ground", "wall", "empty", "empty", "empty", "empty", "empty",
            "empty", "empty", "empty", "empty", "empty", "wall", "ground", "ground", "ground", "ground", "ground", "ground", "ground", "ground", "wall", "wall", "wall", "wall", "wall", "wall",
            "empty", "empty", "empty", "empty", "empty", "wall", "ground", "ground", "ground", "ground", "ground", "ground", "ground", "ground", "ground", "ground", "ground", "ground", "ground", "wall",
            "empty", "empty", "empty", "empty", "empty", "wall", "wall", "wall", "wall", "wall", "wall", "wall", "wall", "wall", "wall", "wall", "wall", "wall", "wall", "wall"
        ]
    },
    "elements": {
        "spawn": {
            "x": 18,
            "y": 18
        },
        "stairs down": {
            "target": "beginner dungeon 3"
        }
    },
    "entities": [
        {
            "type": "monsters.floating paper",
            "components": {
                "position": {
                    "x": 10,
                    "y": 10
                }
            }
        }
    ]
}
